CHANGELOG.rst
LICENSE
MANIFEST.in
README.rst
requirements.txt
setup.py
filehandles/__init__.py
filehandles/filehandles.py
filehandles.egg-info/PKG-INFO
filehandles.egg-info/SOURCES.txt
filehandles.egg-info/dependency_links.txt
filehandles.egg-info/requires.txt
filehandles.egg-info/top_level.txt