Metadata-Version: 1.1
Name: filehandles
Version: 0.1.1
Summary: filehandles is a file handle manager that let you get file handles from different sources.
Home-page: https://github.com/MoseleyBioinformaticsLab/filehandles
Author: Andrey Smelter
Author-email: andrey.smelter@gmail.com
License: BSD
Keywords: filehandle handle open file
Platform: any
Classifier: Development Status :: 4 - Beta
Classifier: Environment :: Console
Classifier: Intended Audience :: Developers
Classifier: Intended Audience :: Science/Research
Classifier: License :: OSI Approved :: BSD License
Classifier: Operating System :: OS Independent
Classifier: Programming Language :: Python :: 2.7
Classifier: Programming Language :: Python :: 3.4
Classifier: Programming Language :: Python :: 3.5
Classifier: Programming Language :: Python :: 3.6
Classifier: Topic :: Software Development :: Libraries :: Python Modules
